uniparser_urmi/__init__.py
uniparser_urmi/__main__.py
uniparser_urmi/analyzer.py
uniparser_urmi/data_nodiacritics/__init__.py
uniparser_urmi/data_nodiacritics/lexemes.txt
uniparser_urmi/data_nodiacritics/paradigms.txt
uniparser_urmi/data_strict/__init__.py
uniparser_urmi/data_strict/lexemes.txt
uniparser_urmi/data_strict/paradigms.txt
uniparser_urmi-1.1.0.dist-info/LICENSE
uniparser_urmi-1.1.0.dist-info/METADATA
uniparser_urmi-1.1.0.dist-info/WHEEL
uniparser_urmi-1.1.0.dist-info/top_level.txt
uniparser_urmi-1.1.0.dist-info/RECORD
