Metadata-Version: 2.1
Name: uniparser-urmi
Version: 1.1.0
Summary: Rule-based morphological analysis for Christian Urmi (North-Eastern Neo-Aramaic)
Home-page: https://github.com/timarkh/uniparser-grammar-urmi
Author: Timofey Arkhangelskiy
Author-email: timarkh@gmail.com
License: UNKNOWN
Project-URL: Bug Tracker, https://github.com/timarkh/uniparser-grammar-urmi/issues
Platform: UNKNOWN
Classifier: Programming Language :: Python :: 3
Classifier: License :: OSI Approved :: MIT License
Classifier: Operating System :: OS Independent
Classifier: Intended Audience :: Science/Research
Classifier: Topic :: Text Processing :: Linguistic
Requires-Python: >=3.7
License-File: LICENSE
Requires-Dist: uniparser-morph (>=2.4.1)
Requires-Dist: importlib-resources
